signal_ICT_SnehFaldu_92510133030/__init__.py
signal_ICT_SnehFaldu_92510133030/operations.py
signal_ICT_SnehFaldu_92510133030/trigonometric_signals.py
signal_ICT_SnehFaldu_92510133030/unitary_signals.py
signal_ict_snehfaldu_92510133030-0.1.0.dist-info/licenses/LICENSE
signal_ict_snehfaldu_92510133030-0.1.0.dist-info/METADATA
signal_ict_snehfaldu_92510133030-0.1.0.dist-info/WHEEL
signal_ict_snehfaldu_92510133030-0.1.0.dist-info/top_level.txt
signal_ict_snehfaldu_92510133030-0.1.0.dist-info/RECORD
