Metadata-Version: 2.4
Name: signal-ict-snehfaldu-92510133030
Version: 0.1.0
Summary: A Python package for unitary, trigonometric signals and operations
Author: StudentName
Author-email: Sneh Faldu <faldusneh@gmail.com>
License: MIT License
Requires-Python: >=3.8
License-File: LICENSE
Requires-Dist: numpy
Requires-Dist: matplotlib
Dynamic: author
Dynamic: license-file
Dynamic: requires-python
